django_torque_semantic_search-0.3.4.dist-info/licenses/LICENSE.md
semantic_search/__init__.py
semantic_search/apps.py
semantic_search/embedding_cache.py
semantic_search/llm.py
semantic_search/models.py
semantic_search/receivers.py
semantic_search/transformers.py
semantic_search/utils.py
semantic_search/version.py
semantic_search/migrations/0001_initial.py
semantic_search/migrations/__init__.py
django_torque_semantic_search-0.3.4.dist-info/METADATA
django_torque_semantic_search-0.3.4.dist-info/WHEEL
django_torque_semantic_search-0.3.4.dist-info/top_level.txt
django_torque_semantic_search-0.3.4.dist-info/RECORD
