Metadata-Version: 2.4
Name: django-torque-semantic-search
Version: 0.3.4
Summary: django app for torque semantic search
Home-page: https://code.librehq.com/ots/mediawiki/semantic-search
Author: Open Tech Strategies, LLC
Author-email: frankduncan@opentechstrategies.com
Classifier: Programming Language :: Python :: 3
Classifier: License :: OSI Approved :: GNU Affero General Public License v3
Classifier: Operating System :: OS Independent
Requires-Python: >=3.11
License-File: LICENSE.md
Requires-Dist: django-torque
Requires-Dist: pgvector
Requires-Dist: orjson
Requires-Dist: luqum
Requires-Dist: ply
Requires-Dist: langchain-text-splitters
Requires-Dist: tenacity
Requires-Dist: httpx
Requires-Dist: tiktoken
Provides-Extra: dev
Requires-Dist: pytest; extra == "dev"
Dynamic: author
Dynamic: author-email
Dynamic: classifier
Dynamic: description
Dynamic: description-content-type
Dynamic: home-page
Dynamic: license-file
Dynamic: provides-extra
Dynamic: requires-dist
Dynamic: requires-python
Dynamic: summary
